damuffin/__init__.py
damuffin/browser.py
damuffin/damuffin.py
damuffin/elog.py
damuffin/hector.py
damuffin/net.py
damuffin/star.py
damuffin/sysinfo.py
damuffin-1.6.1.dist-info/LICENSE
damuffin-1.6.1.dist-info/METADATA
damuffin-1.6.1.dist-info/WHEEL
damuffin-1.6.1.dist-info/top_level.txt
damuffin-1.6.1.dist-info/RECORD
